{
	"pages": [
		{
		    "path" : "pages/home/home",
		    "style" :                                                                                    
		    {
		        "navigationBarTitleText": "",
		        "enablePullDownRefresh": false
		    }
		    
		},
		{
		   "path" : "pages/login/login",
		   "style" :                                                                                    
		   {
			   "navigationBarTitleText": "登录",
			   "enablePullDownRefresh": false
		   }
		   
		}
		,{
            "path" : "pages/register/register",
            "style" :                                                                                    
            {
                "navigationBarTitleText": "注册",
                "enablePullDownRefresh": false
            }
            
        }
        ,{
            "path" : "pages/mine/mine",
            "style" :                                                                                    
            {
                "navigationBarTitleText": "",
                "enablePullDownRefresh": true
            }
            
        }
        ,{
            "path" : "pages/jishi/jishi",
            "style" :                                                                                    
            {
                "navigationBarTitleText": "",
                "enablePullDownRefresh": true
            }
            
        }
        ,{
            "path" : "pages/dingdan/dingdan",
            "style" :                                                                                    
            {
                "navigationBarTitleText": "",
                "enablePullDownRefresh": true
            }
            
        }
        ,{
            "path" : "pages/mine/updatePwd/updatePwd",
            "style" :                                                                                    
            {
                "navigationBarTitleText": "",
                "enablePullDownRefresh": false
            }
            
        }
        ,{
            "path" : "pages/mine/recharge/recharge",
            "style" :                                                                                    
            {
                "navigationBarTitleText": "充值",
                "enablePullDownRefresh": false
            }
            
        }
    ],
	"globalStyle": {
		"navigationBarTextStyle": "black",
		"navigationBarTitleText": "uni-app",
		"navigationBarBackgroundColor": "#f5f5f5",
		"backgroundColor": "#fff",
		"app-plus": {
			"background": "#fff"
		}
	},
	"tabBar": {
		"backgroundColor": "#f5f5f5",
		"list": [
			{
				"pagePath": "pages/home/home",
				"text": "首页"
			},
			{
				"pagePath": "pages/jishi/jishi",
				"text": "技师"
			},
			{
				"pagePath": "pages/dingdan/dingdan",
				"text": "订单"
			},
			{
				"pagePath": "pages/mine/mine",
				"text": "我的"
			}
		]
	}
}
